test_agno/__init__.py
test_agno/log.py
test_agno/server/__init__.py
test_agno/server/__main__.py
test_agno/server/mcp/__init__.py
test_agno/server/mcp/content.py
test_agno/server/mcp/math.py
test_agno/server/mcp/mcp.py
test_agno/server/mcp/resource.py
test_agno/server/mcp/weather.py
test_agno/server/models/__init__.py
test_agno/server/models/models.py
test_agno/server/routers/__init__.py
test_agno/server/routers/admin.py
test_agno/server/routers/user.py
test_agno/server/utils/__init__.py
test_agno/server/utils/auth_backends.py
test_agno/server/utils/database.py
test_agno/server/utils/user_manager.py
test_agno-0.1.0.dist-info/METADATA
test_agno-0.1.0.dist-info/WHEEL
test_agno-0.1.0.dist-info/top_level.txt
test_agno-0.1.0.dist-info/RECORD
